{
    "agent.n.01_1": {
        "is_asleep": false,
        "root_link": {
            "pos": [
                -50.0,
                -50.0,
                -50.0
            ],
            "ori": [
                0.0,
                0.0,
                0.0,
                1.0
            ],
            "lin_vel": [
                0.0,
                0.0,
                0.0
            ],
            "ang_vel": [
                0.0,
                0.0,
                0.0
            ]
        },
        "joint_pos": [
            36.486820220947266,
            55.366390228271484,
            50.00376510620117,
            0.009753976948559284,
            -0.0026535093784332275,
            -0.7478044033050537,
            -7.059454219415784e-05,
            -0.0002603163302410394,
            0.00011121850548079237,
            3.970418674725806e-06,
            -6.458319148805458e-06,
            3.441605804255232e-05,
            1.9059953689575195,
            1.905993938446045,
            -0.9909905791282654,
            -0.9909975528717041,
            1.5710006952285767,
            1.5709997415542603,
            0.915004312992096,
            0.9149976372718811,
            -1.5709986686706543,
            -1.570999264717102,
            0.049999866634607315,
            0.05000000074505806,
            0.04999975487589836,
            0.04999992996454239
        ],
        "joint_vel": [
            5.8150635595666245e-05,
            3.160666165058501e-05,
            -0.0009745137649588287,
            -4.942824489262421e-06,
            0.00015353957132901996,
            0.00010541501978877932,
            0.00014675050624646246,
            -0.00024915230460464954,
            9.924238111125305e-05,
            0.0005520078120753169,
            0.00021507550263777375,
            0.0002446900762151927,
            -0.0005104636074975133,
            0.0004459158517420292,
            6.267760181799531e-05,
            0.00020273044356144965,
            0.00023001823865342885,
            0.00042432075133547187,
            -0.0004930754075758159,
            0.00048655259888619184,
            -0.0002769545535556972,
            -0.00034680514363572,
            3.4419681469444185e-05,
            5.06575179315405e-06,
            -1.2533610060927458e-07,
            5.224245796853211e-06
        ],
        "controllers": {
            "base": {
                "goal_is_valid": true,
                "goal": {
                    "target": [
                        0.0,
                        0.0,
                        0.0
                    ]
                }
            },
            "trunk": {
                "goal_is_valid": true,
                "goal": {
                    "target": [
                        -7.043602818157524e-05,
                        -0.0002607452333904803,
                        0.00011166425974806771,
                        3.353033889652579e-06
                    ]
                }
            },
            "arm_left": {
                "goal_is_valid": true,
                "goal": {
                    "target_pos": [
                        0.5446195602416992,
                        0.3968477249145508,
                        1.446784257888794
                    ],
                    "target_ori_mat": [
                        [
                            -0.006778120994567871,
                            4.651315975934267e-05,
                            0.9999769926071167
                        ],
                        [
                            0.0031175389885902405,
                            -0.9999949932098389,
                            6.76458002999425e-05
                        ],
                        [
                            0.9999721050262451,
                            0.003117925953119993,
                            0.006778061389923096
                        ]
                    ]
                },
                "control_filter": {
                    "past_samples": [
                        [
                            -6.4575883698125836e-06,
                            1.9059962034225464,
                            -0.9909893870353699,
                            1.571000337600708,
                            0.9150072336196899,
                            -1.5709987878799438
                        ],
                        [
                            -5.976186002953909e-06,
                            1.9059951305389404,
                            -0.9909916520118713,
                            1.5710009336471558,
                            0.9150041937828064,
                            -1.5709993839263916
                        ]
                    ],
                    "current_idx": 0,
                    "fully_filled": true
                }
            },
            "gripper_left": {
                "goal_is_valid": true,
                "goal": {
                    "target": [
                        1.0
                    ]
                },
                "vel_filter": {
                    "past_samples": [
                        [
                            7.599591754114954e-06,
                            5.364417575037805e-06
                        ],
                        [
                            -4.470347903406946e-06,
                            -8.940695806813892e-06
                        ],
                        [
                            -1.7881391613627784e-05,
                            -1.8775461285258643e-05
                        ],
                        [
                            1.3411044164968189e-05,
                            1.9222496121074073e-05
                        ],
                        [
                            -1.072883515007561e-05,
                            -6.7055220824840944e-06
                        ]
                    ],
                    "current_idx": 2,
                    "fully_filled": true
                }
            },
            "arm_right": {
                "goal_is_valid": true,
                "goal": {
                    "target_pos": [
                        0.5446233749389648,
                        -0.39683961868286133,
                        1.4439862966537476
                    ],
                    "target_ori_mat": [
                        [
                            0.005850315093994141,
                            -4.025176167488098e-06,
                            0.9999827742576599
                        ],
                        [
                            -0.004663961008191109,
                            -0.9999887943267822,
                            2.3260246962308884e-05
                        ],
                        [
                            0.9999719262123108,
                            -0.004664017353206873,
                            -0.005849957466125488
                        ]
                    ]
                },
                "control_filter": {
                    "past_samples": [
                        [
                            3.442309025558643e-05,
                            1.9059934616088867,
                            -0.9909986853599548,
                            1.5709997415542603,
                            0.9149949550628662,
                            -1.570999264717102
                        ],
                        [
                            3.464561450527981e-05,
                            1.9059934616088867,
                            -0.9909945726394653,
                            1.5709998607635498,
                            0.9149994850158691,
                            -1.5709997415542603
                        ]
                    ],
                    "current_idx": 0,
                    "fully_filled": true
                }
            },
            "gripper_right": {
                "goal_is_valid": true,
                "goal": {
                    "target": [
                        1.0
                    ]
                },
                "vel_filter": {
                    "past_samples": [
                        [
                            -3.4868717193603516e-05,
                            -5.364417575037805e-06
                        ],
                        [
                            3.4868717193603516e-05,
                            1.3411043937594513e-06
                        ],
                        [
                            3.7997957406332716e-05,
                            1.162290482170647e-05
                        ],
                        [
                            -3.4421682357788086e-05,
                            -7.152556918299524e-06
                        ],
                        [
                            3.4421682357788086e-05,
                            7.152556918299524e-06
                        ]
                    ],
                    "current_idx": 2,
                    "fully_filled": true
                }
            }
        },
        "non_kin": {}
    },
    "log.n.01_1": {
        "is_asleep": true,
        "root_link": {
            "pos": [
                -11.78169059753418,
                4.104162693023682,
                0.04653686657547951
            ],
            "ori": [
                0.027027586475014687,
                -0.04016797989606857,
                -0.8259725570678711,
                0.5616275072097778
            ],
            "lin_vel": [
                0.0,
                0.0,
                0.0
            ],
            "ang_vel": [
                0.0,
                0.0,
                0.0
            ]
        },
        "non_kin": {
            "Temperature": {
                "temperature": 23.0
            }
        }
    },
    "log.n.01_2": {
        "is_asleep": true,
        "root_link": {
            "pos": [
                -10.601712226867676,
                3.3650457859039307,
                0.04653662070631981
            ],
            "ori": [
                0.008730689063668251,
                0.04760284721851349,
                0.9833146333694458,
                0.17535729706287384
            ],
            "lin_vel": [
                0.0,
                0.0,
                0.0
            ],
            "ang_vel": [
                0.0,
                0.0,
                0.0
            ]
        },
        "non_kin": {
            "Temperature": {
                "temperature": 23.0
            }
        }
    },
    "log.n.01_3": {
        "is_asleep": true,
        "root_link": {
            "pos": [
                -12.624953269958496,
                3.8018062114715576,
                0.04653631150722504
            ],
            "ori": [
                0.04721562936902046,
                0.010545185767114162,
                0.2225036770105362,
                0.9737308621406555
            ],
            "lin_vel": [
                0.0,
                0.0,
                0.0
            ],
            "ang_vel": [
                0.0,
                0.0,
                0.0
            ]
        },
        "non_kin": {
            "Temperature": {
                "temperature": 23.0
            }
        }
    },
    "log.n.01_4": {
        "is_asleep": true,
        "root_link": {
            "pos": [
                -11.87302303314209,
                4.891508102416992,
                0.0465368889272213
            ],
            "ori": [
                0.037536971271038055,
                0.030553068965673447,
                0.6343182325363159,
                0.7715554237365723
            ],
            "lin_vel": [
                0.0,
                0.0,
                0.0
            ],
            "ang_vel": [
                0.0,
                0.0,
                0.0
            ]
        },
        "non_kin": {
            "Temperature": {
                "temperature": 23.0
            }
        }
    },
    "driveway.n.01_1": {
        "is_asleep": false,
        "root_link": {
            "pos": [
                -12.69985294342041,
                5.707181453704834,
                -0.15000006556510925
            ],
            "ori": [
                0.0,
                0.0,
                0.0,
                1.0
            ]
        },
        "non_kin": {}
    },
    "ax.n.01_1": {
        "is_asleep": true,
        "root_link": {
            "pos": [
                -11.278996467590332,
                3.392551898956299,
                0.01659630984067917
            ],
            "ori": [
                -0.0003794794902205467,
                0.0008441534009762108,
                0.9970709085464478,
                -0.07647912204265594
            ],
            "lin_vel": [
                0.0,
                0.0,
                0.0
            ],
            "ang_vel": [
                0.0,
                0.0,
                0.0
            ]
        },
        "non_kin": {
            "SlicerActive": {
                "value": true,
                "previously_touching": false,
                "delay_counter": 0
            }
        }
    },
    "chopping_block.n.01_1": {
        "is_asleep": true,
        "root_link": {
            "pos": [
                -12.367258071899414,
                3.2209420204162598,
                0.0499899797141552
            ],
            "ori": [
                8.169218199327588e-05,
                -1.4407396520255134e-05,
                0.9730867743492126,
                -0.23043948411941528
            ],
            "lin_vel": [
                0.0,
                0.0,
                0.0
            ],
            "ang_vel": [
                0.0,
                0.0,
                0.0
            ]
        },
        "non_kin": {}
    }
}